easymultilogging.py
easymultilogging-0.0.6.dist-info/LICENSE
easymultilogging-0.0.6.dist-info/METADATA
easymultilogging-0.0.6.dist-info/WHEEL
easymultilogging-0.0.6.dist-info/top_level.txt
easymultilogging-0.0.6.dist-info/RECORD
