Metadata-Version: 2.1
Name: easymultilogging
Version: 0.0.6
Summary: A package to help multiLogging in Python.
Home-page: UNKNOWN
Author: Praneeth Ponnekanti
Author-email: praneeth.ponnekanti@gmail.com
License: UNKNOWN
Platform: UNKNOWN
Classifier: Programming Language :: Python :: 3
Classifier: License :: OSI Approved :: MIT License
Classifier: Operating System :: OS Independent
Requires-Python: >=3.6
